trove_newspaper_harvester/__init__.py
trove_newspaper_harvester/_modidx.py
trove_newspaper_harvester/cli.py
trove_newspaper_harvester/core.py
trove_newspaper_harvester-0.7.2.dist-info/LICENSE
trove_newspaper_harvester-0.7.2.dist-info/METADATA
trove_newspaper_harvester-0.7.2.dist-info/WHEEL
trove_newspaper_harvester-0.7.2.dist-info/entry_points.txt
trove_newspaper_harvester-0.7.2.dist-info/top_level.txt
trove_newspaper_harvester-0.7.2.dist-info/RECORD
