Metadata-Version: 2.1
Name: trove-newspaper-harvester
Version: 0.7.2
Summary: Tool for bulk harvests of digitised newspaper articles from Trove
Home-page: https://github.com/wragge/trove-newspaper-harvester
Author: Tim Sherratt
Author-email: tim@timsherratt.org
License: MIT License
Keywords: nbdev jupyter notebook python
Platform: UNKNOWN
Classifier: Development Status :: 4 - Beta
Classifier: Intended Audience :: Developers
Classifier: Natural Language :: English
Classifier: Programming Language :: Python :: 3.8
Classifier: Programming Language :: Python :: 3.9
Classifier: Programming Language :: Python :: 3.10
Classifier: License :: OSI Approved :: MIT License
Requires-Python: >=3.8
Requires-Dist: requests-cache
Requires-Dist: arrow
Requires-Dist: tqdm
Requires-Dist: pillow
Requires-Dist: beautifulsoup4
Requires-Dist: lxml
Requires-Dist: html2text
Requires-Dist: trove-query-parser
Requires-Dist: trove-newspaper-images
Requires-Dist: rocrate
Provides-Extra: dev
Requires-Dist: jupyterlab ; extra == 'dev'
Requires-Dist: nbdev ; extra == 'dev'
Requires-Dist: jupyterlab-code-formatter ; extra == 'dev'
Requires-Dist: black ; extra == 'dev'
Requires-Dist: isort ; extra == 'dev'
Requires-Dist: python-dotenv ; extra == 'dev'
Requires-Dist: ipywidgets ; extra == 'dev'
Requires-Dist: fastcore ; extra == 'dev'
Requires-Dist: pandas ; extra == 'dev'
